easybioinfo/__init__.py
easybioinfo/sequences.py
easybioinfo-0.2.1.dist-info/LICENSE
easybioinfo-0.2.1.dist-info/METADATA
easybioinfo-0.2.1.dist-info/WHEEL
easybioinfo-0.2.1.dist-info/top_level.txt
easybioinfo-0.2.1.dist-info/RECORD
