Metadata-Version: 2.1
Name: easybioinfo
Version: 0.2.1
Summary: Convenient python functions for bioinformatics
Home-page: https://github.com/marco-mariotti/easybioinfo
Author: Marco Mariotti
Author-email: marco.mariotti@ub.edu
License: UNKNOWN
Platform: UNKNOWN
Classifier: Programming Language :: Python :: 3
Classifier: License :: OSI Approved :: MIT License
Classifier: Operating System :: OS Independent
Requires-Python: >=3.6
License-File: LICENSE
